README.md
setup.py
dlpy/__init__.py
dlpy/attribute_utils.py
dlpy/audio.py
dlpy/blocks.py
dlpy/data_clean.py
dlpy/embedding_model.py
dlpy/image_captioning.py
dlpy/image_embedding.py
dlpy/images.py
dlpy/layers.py
dlpy/lr_scheduler.py
dlpy/metrics.py
dlpy/model.py
dlpy/mzmodel.py
dlpy/mzmodel_plot.py
dlpy/network.py
dlpy/sequential.py
dlpy/speech.py
dlpy/speech_utils.py
dlpy/splitting.py
dlpy/timeseries.py
dlpy/utils.py
dlpy/applications/__init__.py
dlpy/applications/application_utils.py
dlpy/applications/applications.py
dlpy/applications/darknet.py
dlpy/applications/densenet.py
dlpy/applications/efficientnet.py
dlpy/applications/enet.py
dlpy/applications/inception.py
dlpy/applications/mobilenet.py
dlpy/applications/rcnn.py
dlpy/applications/resnet.py
dlpy/applications/shufflenet.py
dlpy/applications/unet.py
dlpy/applications/vgg.py
dlpy/applications/yolo.py
dlpy/caffe_models/__init__.py
dlpy/caffe_models/model_lenet.py
dlpy/caffe_models/model_resnet101.py
dlpy/caffe_models/model_resnet152.py
dlpy/caffe_models/model_resnet50.py
dlpy/caffe_models/model_vgg16.py
dlpy/caffe_models/model_vgg19.py
dlpy/datasources/coco.names
dlpy/datasources/data_clean_replacements.txt
dlpy/datasources/imagenet_label.sas7bdat
dlpy/datasources/imagenet_labels.csv
dlpy/datasources/mapping.json
dlpy/datasources/mzscore.yaml
dlpy/datasources/mztrain.yaml
dlpy/keras_models/__init__.py
dlpy/keras_models/model_inceptionv3.py
dlpy/model_conversion/__init__.py
dlpy/model_conversion/keras_utils.py
dlpy/model_conversion/model_conversion_utils.py
dlpy/model_conversion/onnx_graph.py
dlpy/model_conversion/onnx_transforms.py
dlpy/model_conversion/sas_caffe_parse.py
dlpy/model_conversion/sas_keras_parse.py
dlpy/model_conversion/sas_onnx_parse.py
dlpy/model_conversion/write_caffe_model_parm.py
dlpy/model_conversion/write_keras_model_parm.py
dlpy/model_conversion/write_onnx_model.py
dlpy/model_conversion/write_sas_code.py
dlpy/tests/__init__.py
dlpy/tests/__main__.py
dlpy/tests/test_applications.py
sas_dlpy.egg-info/PKG-INFO
sas_dlpy.egg-info/SOURCES.txt
sas_dlpy.egg-info/dependency_links.txt
sas_dlpy.egg-info/requires.txt
sas_dlpy.egg-info/top_level.txt